[
  {
    "id": 1,
    "name": "Sakib Al Hasan",
    "email": "sakib.75@cricket.bd",
    "phone": "‪+880 1711-223344‬",
    "company": {
      "name": "Grameenphone",
      "bs": "Brand Ambassador"
    }
  },
  {
    "id": 2,
    "name": "Hasan",
    "email": "hasan.dev@pathao.com",
    "phone": "‪+880 1912-345678‬",
    "company": {
      "name": "Pathao",
      "bs": "Ride Sharing Tech"
    }
  },
  {
    "id": 3,
    "name": "Shakibul Hasan",
    "email": "hasan.u@bkash.com",
    "phone": "‪+880 1819-001122‬",
    "company": {
      "name": "bKash Ltd",
      "bs": "Mobile Financial Services"
    }
  },
  {
    "id": 4,
    "name": "Dr. Sabur Khan",
    "email": "dr.sabur@square.edu.bd",
    "phone": "‪+880 1555-998877‬",
    "company": {
      "name": "Square Hospital",
      "bs": "Healthcare"
    }
  },
  {
    "id": 5,
    "name": "Aminul Islam",
    "email": "rafiq@daraz.com.bd",
    "phone": "‪+880 1677-445566‬",
    "company": {
      "name": "Daraz Bangladesh",
      "bs": "E-Commerce"
    }
  },
  {
    "id": 6,
    "name": "Tasnim Jarinand",
    "email": "tasnim@brac.net",
    "phone": "‪+880 1300-112233‬",
    "company": {
      "name": "BRAC NGO",
      "bs": "Social Development"
    }
  }
]